InteracTor.py
interactor_tools-0.1.0.dist-info/METADATA
interactor_tools-0.1.0.dist-info/WHEEL
interactor_tools-0.1.0.dist-info/entry_points.txt
interactor_tools-0.1.0.dist-info/RECORD
