Metadata-Version: 2.3
Name: InteracTor-tools
Version: 0.1.0
Summary: InteracTor is a tool for molecular structure analysis and conversion, allowing the extraction of interactions and relevant features for biochemical studies
License: MIT
Author: Jose Cleydson F Silva jferreiradasilva@ufl.edu
Requires-Python: >=3.8,<4.0
Classifier: License :: OSI Approved :: MIT License
Classifier: Programming Language :: Python :: 3
Classifier: Programming Language :: Python :: 3.8
Classifier: Programming Language :: Python :: 3.9
Classifier: Programming Language :: Python :: 3.10
Classifier: Programming Language :: Python :: 3.11
Classifier: Programming Language :: Python :: 3.12
Classifier: Programming Language :: Python :: 3.13
